[{"id":1,"name":"动画","subclasse":[{"id":106,"name":"动画短片"},{"id":108,"name":"MMD·3D"},{"id":109,"name":"动画合集"},{"id":107,"name":"MAD·AMV"},{"id":67,"name":"新番连载"}]},{"id":58,"name":"音乐","subclasse":[{"id":101,"name":"演唱·乐器"},{"id":104,"name":"ACG音乐"},{"id":102,"name":"宅舞"},{"id":103,"name":"Vocaloid"},{"id":105,"name":"流行音乐"}]},{"id":59,"name":"游戏","subclasse":[{"id":84,"name":"实况解说"},{"id":71,"name":"Flash游戏"},{"id":85,"name":"英雄联盟"},{"id":83,"name":"游戏集锦"},{"id":72,"name":"Mugen"}]},{"id":60,"name":"娱乐","subclasse":[{"id":86,"name":"生活娱乐"},{"id":87,"name":"鬼畜调教"},{"id":88,"name":"萌宠"},{"id":89,"name":"美食"}]},{"id":63,"name":"文章","subclasse":[{"id":75,"name":"漫画·小说"},{"id":110,"name":"综合"},{"id":74,"name":"动漫文化"},{"id":76,"name":"页游资料"},{"id":73,"name":"工作·情感"}]},{"id":68,"name":"影视","subclasse":[{"id":100,"name":"纪录片"},{"id":98,"name":"综艺"},{"id":97,"name":"剧集"},{"id":96,"name":"电影"},{"id":99,"name":"特摄·霹雳"}]},{"id":69,"name":"体育","subclasse":[{"id":93,"name":"惊奇体育"},{"id":94,"name":"足球"},{"id":95,"name":"篮球"}]},{"id":70,"name":"科技","subclasse":[{"id":92,"name":"军事"},{"id":91,"name":"数码"},{"id":90,"name":"科普"}]}]